gmanka_yml/__init__.py
gmanka_yml-23.0.5.dist-info/METADATA
gmanka_yml-23.0.5.dist-info/WHEEL
gmanka_yml-23.0.5.dist-info/RECORD
